sparkmanager/__init__.py
sparkmanager/eventlog.py
sparkmanager/manager.py
functionalizer-1.0.0.dist-info/entry_points.txt
functionalizer-1.0.0.dist-info/WHEEL
functionalizer-1.0.0.dist-info/RECORD
functionalizer-1.0.0.dist-info/METADATA
functionalizer-1.0.0.dist-info/licenses/AUTHORS.txt
functionalizer-1.0.0.dist-info/licenses/LICENSE.txt
functionalizer/circuit.py
functionalizer/schema.py
functionalizer/cluster.py
functionalizer/__init__.py
functionalizer/definitions.py
functionalizer/core.py
functionalizer/commands.py
functionalizer/version.py
functionalizer/tools/__init__.py
functionalizer/tools/coalesce.py
functionalizer/tools/compare.py
functionalizer/tools/compare_nodesets.py
functionalizer/tools/validation/touches_plot.py
functionalizer/filters/__init__.py
functionalizer/filters/definitions.py
functionalizer/filters/helpers.py
functionalizer/filters/udfs/_udfs.cpp
functionalizer/filters/udfs/__init__.py
functionalizer/filters/udfs/CMakeLists.txt
functionalizer/filters/udfs/_udfs.cpython-312-x86_64-linux-gnu.so
functionalizer/filters/udfs/parameters.py
functionalizer/filters/implementations/__init__.py
functionalizer/filters/implementations/reduce_and_cut.py
functionalizer/filters/implementations/synapse_id.py
functionalizer/filters/implementations/gap_junction.py
functionalizer/filters/implementations/touch.py
functionalizer/filters/implementations/synapse_properties.py
functionalizer/filters/implementations/synapse_reposition.py
functionalizer/filters/implementations/spine_length.py
functionalizer/filters/implementations/bouton_distance.py
functionalizer/filters/implementations/spine_morphologies.py
functionalizer/filters/implementations/soma_distance.py
functionalizer/data/default.properties
functionalizer/data/desktop.properties
functionalizer/data/cluster/core-site.xml
functionalizer/data/cluster/log4j.properties
functionalizer/data/cluster/hdfs-site.xml
functionalizer/utils/spark.py
functionalizer/utils/__init__.py
functionalizer/utils/filesystem.py
functionalizer/utils/checkpointing.py
functionalizer/utils/_misc.py
functionalizer/utils/conf.py
functionalizer/io/circuit.py
functionalizer/io/morphologies.py
functionalizer/io/__init__.py
