Metadata-Version: 2.1
Name: functionalizer
Version: 1.0.0
Summary: A PySpark implementation of the Blue Brain Project Functionalizer
Author-Email: BlueBrain HPC <bbp-ou-hpc@epfl.ch>
Maintainer-Email: Matthias Wolf <matthias.wolf@epfl.ch>, Fernando Pereira <fernando.pereira@epfl.ch>
License:                                  Apache License
Classifier: Development Status :: 4 - Beta
Classifier: Programming Language :: Python
Classifier: Programming Language :: Python :: 3
Classifier: Topic :: Scientific/Engineering
Classifier: License :: OSI Approved :: Apache Software License
Project-URL: Homepage, https://github.com/BlueBrain/functionalizer
Project-URL: Repository, https://github.com/BlueBrain/functionalizer
Project-URL: Issues, https://github.com/BlueBrain/functionalizer/issues
Project-URL: Tracker, https://github.com/BlueBrain/functionalizer/issues
Requires-Dist: fz-td-recipe>=0.1.3.dev0
Requires-Dist: h5py
Requires-Dist: hdfs
Requires-Dist: jprops
Requires-Dist: morphio
Requires-Dist: mpi4py
Requires-Dist: libsonata
Requires-Dist: numpy<2
Requires-Dist: packaging
Requires-Dist: pandas
Requires-Dist: pyarrow<15
Requires-Dist: pyspark>=3
